main.py
setup.py
tarsie.egg-info/PKG-INFO
tarsie.egg-info/SOURCES.txt
tarsie.egg-info/dependency_links.txt
tarsie.egg-info/requires.txt
tarsie.egg-info/top_level.txt